odoo/addons/event_track_location_overlap/README.rst
odoo/addons/event_track_location_overlap/__init__.py
odoo/addons/event_track_location_overlap/__manifest__.py
odoo/addons/event_track_location_overlap/i18n/es.po
odoo/addons/event_track_location_overlap/i18n/event_track_location_overlap.pot
odoo/addons/event_track_location_overlap/i18n/it.po
odoo/addons/event_track_location_overlap/models/__init__.py
odoo/addons/event_track_location_overlap/models/event_track.py
odoo/addons/event_track_location_overlap/models/event_track_location.py
odoo/addons/event_track_location_overlap/readme/CONFIGURE.rst
odoo/addons/event_track_location_overlap/readme/CONTRIBUTORS.rst
odoo/addons/event_track_location_overlap/readme/DESCRIPTION.rst
odoo/addons/event_track_location_overlap/readme/USAGE.rst
odoo/addons/event_track_location_overlap/static/description/icon.png
odoo/addons/event_track_location_overlap/static/description/index.html
odoo/addons/event_track_location_overlap/tests/__init__.py
odoo/addons/event_track_location_overlap/tests/test_overlap.py
odoo/addons/event_track_location_overlap/views/event_track_location_view.xml
odoo13_addon_event_track_location_overlap-13.0.1.0.1.dev6.dist-info/METADATA
odoo13_addon_event_track_location_overlap-13.0.1.0.1.dev6.dist-info/WHEEL
odoo13_addon_event_track_location_overlap-13.0.1.0.1.dev6.dist-info/top_level.txt
odoo13_addon_event_track_location_overlap-13.0.1.0.1.dev6.dist-info/RECORD
